[
  {
    "title": "多人出游✅10房独栋别墅+海景+泳池谁不爱！",
    "url": "http://xhslink.com/o/3nIIPuJHoTU",
    "category": "鼎龙湾"
  },
  {
    "title": "鼎龙湾zui美的别墅🏡",
    "url": "http://xhslink.com/o/nIGivy4HIG",
    "category": "鼎龙湾"
  },
  {
    "title": "湛江鼎龙湾｜步行直达的海边别墅",
    "url": "http://xhslink.com/o/Wc3e1Mw4ue",
    "category": "鼎龙湾"
  },
  {
    "title": "吴川！海边小院（29号开始空）",
    "url": "http://xhslink.com/o/52MdMkGiitF",
    "category": "鼎龙湾"
  },
  {
    "title": "湛江团建 / 家庭游！全海景别墅",
    "url": "http://xhslink.com/o/1dqExFsf8dW",
    "category": "鼎龙湾"
  },
  {
    "title": "阳江海陵岛📍新开！直接锁死这家🔥",
    "url": "http://xhslink.com/o/21m6uIhTKaO",
    "category": "海陵岛"
  }
]
